elements/__init__.py
elements/api_resource.py
elements/elements_client.py
elements/elements_object.py
elements/elements_response.py
elements/errors.py
elements/object_types.py
elements/six.py
elements/util.py
elements/version.py
elements/certs/cacert.pem
elements/resources/__init__.py
elements/resources/charge.py
elements/resources/checkout_session.py
elements/resources/client_token.py
elements/resources/customer.py
elements/resources/dispute.py
elements/resources/payment_method.py
elements/resources/payment_method_gateway.py
elements/resources/refund.py
elements/resources/token.py
elements_pay-1.0.3.dist-info/LICENSE
elements_pay-1.0.3.dist-info/METADATA
elements_pay-1.0.3.dist-info/WHEEL
elements_pay-1.0.3.dist-info/top_level.txt
elements_pay-1.0.3.dist-info/RECORD
