Metadata-Version: 2.1
Name: elements-pay
Version: 1.0.3
Summary: The Elements Pay Python SDK
Author: Elements
Requires-Python: >=2.7, !=3.0.*, !=3.1.*, !=3.2.*, !=3.3.*, !=3.4.*
License-File: LICENSE
Requires-Dist: requests[security] (>=2.20) ; python_version < "3.0"
Requires-Dist: requests (>=2.20) ; python_version >= "3.0"
